qtutils/UiLoader.py
qtutils/__init__.py
qtutils/__version__.py
qtutils/auto_scroll_to_end.py
qtutils/disconnect_contextmanager.py
qtutils/invoke_in_main.py
qtutils/locking.py
qtutils/outputbox.py
qtutils/qsettings_wrapper.py
qtutils/qt.py
qtutils/fonts/__init__.py
qtutils/fonts/ubuntu-font-family/CONTRIBUTING.txt
qtutils/fonts/ubuntu-font-family/FONTLOG.txt
qtutils/fonts/ubuntu-font-family/LICENCE-FAQ.txt
qtutils/fonts/ubuntu-font-family/LICENCE.txt
qtutils/fonts/ubuntu-font-family/README.txt
qtutils/fonts/ubuntu-font-family/TRADEMARKS.txt
qtutils/fonts/ubuntu-font-family/Ubuntu-B.ttf
qtutils/fonts/ubuntu-font-family/Ubuntu-BI.ttf
qtutils/fonts/ubuntu-font-family/Ubuntu-C.ttf
qtutils/fonts/ubuntu-font-family/Ubuntu-L.ttf
qtutils/fonts/ubuntu-font-family/Ubuntu-LI.ttf
qtutils/fonts/ubuntu-font-family/Ubuntu-M.ttf
qtutils/fonts/ubuntu-font-family/Ubuntu-MI.ttf
qtutils/fonts/ubuntu-font-family/Ubuntu-R.ttf
qtutils/fonts/ubuntu-font-family/Ubuntu-RI.ttf
qtutils/fonts/ubuntu-font-family/Ubuntu-Th.ttf
qtutils/fonts/ubuntu-font-family/UbuntuMono-B.ttf
qtutils/fonts/ubuntu-font-family/UbuntuMono-BI.ttf
qtutils/fonts/ubuntu-font-family/UbuntuMono-R.ttf
qtutils/fonts/ubuntu-font-family/UbuntuMono-RI.ttf
qtutils/fonts/ubuntu-font-family/copyright.txt
qtutils/icons/__init__.py
qtutils/icons/_icons_pyqt5.py
qtutils/icons/_icons_pyside6.py
qtutils-4.0.0.dist-info/LICENSE.txt
qtutils-4.0.0.dist-info/METADATA
qtutils-4.0.0.dist-info/WHEEL
qtutils-4.0.0.dist-info/top_level.txt
qtutils-4.0.0.dist-info/RECORD
