Metadata-Version: 2.1
Name: qtutils
Version: 4.0.0
Summary: PySide6/PyQt5 abstraction layer, mulithreading and UI loader utilities, icon set, and more
Author-email: Philip Starkey <threepineapples@gmail.com>, Chris Billington <chrisjbillington@gmail.com>
License: Copyright (c) 2013, Christopher Billington, Philip Starkey
Project-URL: Homepage, https://github.com/philipstarkey/qtutils
Project-URL: Documentation, https://readthedocs.org/projects/qtutils/
Project-URL: Repository, https://github.com/philipstarkey/qtutils
Project-URL: Downloads, https://pypi.org/project/qtutils/
Project-URL: Tracker, https://github.com/philipstarkey/qtutils/issues
Keywords: Qt,PyQt,PySide
Classifier: License :: OSI Approved :: BSD License
Classifier: Programming Language :: Python :: 3 :: Only
Requires-Python: >=3.8
License-File: LICENSE.txt
Requires-Dist: setuptools_scm>=8
Provides-Extra: pyqt5
Requires-Dist: PyQt5; extra == "pyqt5"
Provides-Extra: pyside6
Requires-Dist: PySide6; extra == "pyside6"
Provides-Extra: docs
Requires-Dist: PyQt5; extra == "docs"
Requires-Dist: PySide6; extra == "docs"
Requires-Dist: Sphinx>=7.0.0; extra == "docs"
Requires-Dist: sphinx-rtd-theme>=1.3.0; extra == "docs"
Requires-Dist: recommonmark>=0.7.1; extra == "docs"
Requires-Dist: myst-parser; extra == "docs"
